checkBest/__init__.py
checkBest/check.py
checkBest-0.1.1.dist-info/METADATA
checkBest-0.1.1.dist-info/WHEEL
checkBest-0.1.1.dist-info/top_level.txt
checkBest-0.1.1.dist-info/RECORD
