Metadata-Version: 2.1
Name: checkBest
Version: 0.1.1
Summary: A collection of Python functions designed to validate various types of input. These functions can be used to ensure that user inputs such as passwords, emails, and other required fields meet specific criteria.
Home-page: https://github.com/Bestsenator/checkBest
Author: Bestsenator
Author-email: senator136019@gmail.com
Classifier: Programming Language :: Python :: 3
Classifier: License :: OSI Approved :: MIT License
Classifier: Operating System :: OS Independent
Requires-Python: >=3.6
Requires-Dist: regex ==2023.10.3
Requires-Dist: jdatetime ==4.1.1
